sibyl/__init__.py
sibyl/dataexplorer.py
sibyl/example_automl.py
sibyl/example_customsteps.py
sibyl/predictor.py
sibyl/encoders/__init__.py
sibyl/encoders/omniencoder.py
sibyl/models/__init__.py
sibyl/models/catboostwrapper.py
sibyl/models/keraslean.py
sibyl/models/kerasmodels.py
sibyl/models/lightgbmwrapper.py
sibyl_ai-1.0.15.dist-info/METADATA
sibyl_ai-1.0.15.dist-info/WHEEL
sibyl_ai-1.0.15.dist-info/top_level.txt
sibyl_ai-1.0.15.dist-info/RECORD
