Metadata-Version: 2.1
Name: sibyl-ai
Version: 1.0.15
Summary: Wrapper for SKLearn Pipeline with Auto ML features
Home-page: https://github.com/sirbradflies/Sibyl
Author: Francesco Baldisserri
Author-email: fbaldisserri@gmail.com
License: MIT
Keywords: AI ML Pipeline Wrapper AutoML
Requires-Dist: joblib
Requires-Dist: numpy
Requires-Dist: pandas
Requires-Dist: scipy
Requires-Dist: scikit-learn
Requires-Dist: tensorflow
Requires-Dist: catboost
Requires-Dist: seaborn
Requires-Dist: lightgbm
Requires-Dist: matplotlib
